dash_select/Select.py
dash_select/__init__.py
dash_select/_imports_.py
dash_select/dash_select.min.js
dash_select/dash_select.min.js.map
dash_select/metadata.json
dash_select/package-info.json
dash_select-1.0.1.dist-info/LICENSE
dash_select-1.0.1.dist-info/METADATA
dash_select-1.0.1.dist-info/WHEEL
dash_select-1.0.1.dist-info/top_level.txt
dash_select-1.0.1.dist-info/RECORD
