Metadata-Version: 2.1
Name: dash-select
Version: 1.0.1
Summary: A Dash wrapper for <select> component
Home-page: UNKNOWN
Author: Ruslan Khairutdinov <ruslan.khairutdinov22@gmail.com>
License: MIT
Project-URL: Github, https://github.com/ruslankhayrut/DashSelect
Platform: UNKNOWN
Classifier: Framework :: Dash
